[
    {
        "ProjectImg":"Comeing Soon...",
        "ProjectName":"Api Data Show",
        "Discription":"Wed App"
    },
    {
        "ProjectImg":"Comeing Soon...",
        "ProjectName":"ToDo",
        "Discription":"Wed App"
    },
    {
        "ProjectImg":"Comeing Soon...",
        "ProjectName":"Landing Page",
        "Discription":"Wordpress"
    },
    {
        "ProjectImg":"Comeing Soon...",
        "ProjectName":"Real Estate Page",
        "Discription":"Web Page"
    },
    {
        "ProjectImg":"Comeing Soon...",
        "ProjectName":"Email Template",
        "Discription":"Web Page"
    },
    {
        "ProjectImg":"Comeing Soon...",
        "ProjectName":"Real Estate Landing Page",
        "Discription":"Web Page"
    }
    
]